pepperpy_poetry/commands.py
pepperpy_poetry/config.py
pepperpy_poetry/dependency.py
pepperpy_poetry/generators.py
pepperpy_poetry/plugin.py
pepperpy_poetry-0.4.1.dist-info/LICENSE
pepperpy_poetry-0.4.1.dist-info/METADATA
pepperpy_poetry-0.4.1.dist-info/WHEEL
pepperpy_poetry-0.4.1.dist-info/entry_points.txt
pepperpy_poetry-0.4.1.dist-info/RECORD
