Metadata-Version: 2.3
Name: pepperpy-poetry
Version: 0.4.1
Summary: A Poetry plugin for shared configuration management across multiple projects in the pepperpy ecosystem
License: MIT
Keywords: poetry,plugin,configuration,management,pepperpy
Author: Felipe Pimentel
Author-email: felipe.pimentel@gmail.com
Maintainer: Felipe Pimentel
Maintainer-email: felipe.pimentel@gmail.com
Requires-Python: >=3.12,<4.0
Classifier: Development Status :: 4 - Beta
Classifier: Environment :: Plugins
Classifier: Intended Audience :: Developers
Classifier: License :: OSI Approved :: MIT License
Classifier: Natural Language :: English
Classifier: Operating System :: OS Independent
Classifier: Programming Language :: Python :: 3
Classifier: Programming Language :: Python :: 3.12
Classifier: Programming Language :: Python :: 3.13
Classifier: Programming Language :: Python :: 3.10
Classifier: Programming Language :: Python :: 3.11
Classifier: Programming Language :: Python :: 3.9
Classifier: Topic :: Software Development :: Build Tools
Classifier: Topic :: Software Development :: Libraries :: Python Modules
Requires-Dist: click (>=8.1.8,<9.0.0)
Requires-Dist: poetry (>=2.0.1,<3.0.0)
Requires-Dist: pyyaml (>=6.0.2,<7.0.0)
Requires-Dist: toml (>=0.10.2,<0.11.0)
Project-URL: Documentation, https://felipepimentel.github.io/pepperpy-poetry
Project-URL: Homepage, https://github.com/felipepimentel/pepperpy-poetry
Project-URL: Repository, https://github.com/felipepimentel/pepperpy-poetry
